pinax/__init__.py
pinax/pages/__init__.py
pinax/pages/admin.py
pinax/pages/apps.py
pinax/pages/compat.py
pinax/pages/conf.py
pinax/pages/forms.py
pinax/pages/hooks.py
pinax/pages/managers.py
pinax/pages/models.py
pinax/pages/urls.py
pinax/pages/utils.py
pinax/pages/views.py
pinax/pages/migrations/0001_initial.py
pinax/pages/migrations/0002_auto_20180122_1445.py
pinax/pages/migrations/0003_auto_20180122_1446.py
pinax/pages/migrations/__init__.py
pinax/pages/tests/__init__.py
pinax/pages/tests/models.py
pinax/pages/tests/tests.py
pinax/pages/tests/urls.py
pinax_pages-0.5.0.dist-info/DESCRIPTION.rst
pinax_pages-0.5.0.dist-info/METADATA
pinax_pages-0.5.0.dist-info/RECORD
pinax_pages-0.5.0.dist-info/WHEEL
pinax_pages-0.5.0.dist-info/metadata.json
pinax_pages-0.5.0.dist-info/top_level.txt
