Metadata-Version: 2.0
Name: pinax-pages
Version: 0.5.0
Summary: a Django pages app
Home-page: https://github.com/pinax/pinax-pages/
Author: Pinax Team
Author-email: team@pinaxproject.com
License: MIT
Platform: UNKNOWN
Classifier: Development Status :: 4 - Beta
Classifier: Environment :: Web Environment
Classifier: Framework :: Django
Classifier: Intended Audience :: Developers
Classifier: License :: OSI Approved :: MIT License
Classifier: Operating System :: OS Independent
Classifier: Programming Language :: Python
Classifier: Programming Language :: Python :: 2
Classifier: Programming Language :: Python :: 3
Classifier: Topic :: Software Development :: Libraries :: Python Modules
Requires-Dist: django-appconf (>=1.0.1)
